MANIFEST.in
README.md
setup.py
EasyI3Status.egg-info/PKG-INFO
EasyI3Status.egg-info/SOURCES.txt
EasyI3Status.egg-info/dependency_links.txt
EasyI3Status.egg-info/entry_points.txt
EasyI3Status.egg-info/requires.txt
EasyI3Status.egg-info/top_level.txt
easyi3status/__init__.py
easyi3status/config.cfg
easyi3status/modules/date.py
easyi3status/modules/imap.py
easyi3status/modules/jiraIssues.py