Metadata-Version: 1.0
Name: EasyI3Status
Version: 0.0.9
Summary: Easy status bar for i3 window manager.
Home-page: https://bitbucket.org/aecepoglu/easyi3status
Author: Ahmet Emre Cepoglu
Author-email: aecepoglu@fastmail.fm
License: UNKNOWN
Platform: UNKNOWN
